{"added_at":"2023-09-08T03:56:44Z","added_by":{"external_urls":{"spotify":"https://open.spotify.com/user/31g2xvygqvt2vimbh46mgwuso6ju"},"href":"https://api.spotify.com/v1/users/31g2xvygqvt2vimbh46mgwuso6ju","id":"31g2xvygqvt2vimbh46mgwuso6ju","type":"user","uri":"spotify:user:31g2xvygqvt2vimbh46mgwuso6ju"},"is_local":false,"primary_color":null,"track":{"album":{"album_type":"single","artists":[{"external_urls":{"spotify":"https://open.spotify.com/artist/2jOm3cYujQx6o1dxuiuqaX"},"href":"https://api.spotify.com/v1/artists/2jOm3cYujQx6o1dxuiuqaX","id":"2jOm3cYujQx6o1dxuiuqaX","name":"RIIZE","type":"artist","uri":"spotify:artist:2jOm3cYujQx6o1dxuiuqaX"}],"available_markets":["AR","AU","AT","BE","BO","BR","BG","CA","CL","CO","CR","CY","CZ","DK","DO","DE","EC","EE","SV","FI","FR","GR","GT","HN","HK","HU","IS","IE","IT","LV","LT","LU","MY","MT","MX","NL","NZ","NI","NO","PA","PY","PE","PH","PL","PT","SG","SK","ES","SE","CH","TW","TR","UY","US","GB","AD","LI","MC","ID","JP","TH","VN","RO","IL","ZA","SA","AE","BH","QA","OM","KW","EG","MA","DZ","TN","LB","JO","PS","IN","BY","KZ","MD","UA","AL","BA","HR","ME","MK","RS","SI","KR","BD","PK","LK","GH","KE","NG","TZ","UG","AG","AM","BS","BB","BZ","BT","BW","BF","CV","CW","DM","FJ","GM","GE","GD","GW","GY","HT","JM","KI","LS","LR","MW","MV","ML","MH","FM","NA","NR","NE","PW","PG","WS","SM","ST","SN","SC","SL","SB","KN","LC","VC","SR","TL","TO","TT","TV","VU","AZ","BN","BI","KH","CM","TD","KM","GQ","SZ","GA","GN","KG","LA","MO","MR","MN","NP","RW","TG","UZ","ZW","BJ","MG","MU","MZ","AO","CI","DJ","ZM","CD","CG","IQ","LY","TJ","VE","ET","XK"],"external_urls":{"spotify":"https://open.spotify.com/album/3E5VbhGdSMotB0oQ3LwT9k"},"href":"https://api.spotify.com/v1/albums/3E5VbhGdSMotB0oQ3LwT9k","id":"3E5VbhGdSMotB0oQ3LwT9k","images":[{"height":640,"url":"https://i.scdn.co/image/ab67616d0000b27308f9aed64208e0f8d9e10f0e","width":640},{"height":300,"url":"https://i.scdn.co/image/ab67616d00001e0208f9aed64208e0f8d9e10f0e","width":300},{"height":64,"url":"https://i.scdn.co/image/ab67616d0000485108f9aed64208e0f8d9e10f0e","width":64}],"name":"Get A Guitar","release_date":"2023-09-04","release_date_precision":"day","total_tracks":2,"type":"album","uri":"spotify:album:3E5VbhGdSMotB0oQ3LwT9k"},"artists":[{"external_urls":{"spotify":"https://open.spotify.com/artist/2jOm3cYujQx6o1dxuiuqaX"},"href":"https://api.spotify.com/v1/artists/2jOm3cYujQx6o1dxuiuqaX","id":"2jOm3cYujQx6o1dxuiuqaX","name":"RIIZE","type":"artist","uri":"spotify:artist:2jOm3cYujQx6o1dxuiuqaX"}],"available_markets":["AR","AU","AT","BE","BO","BR","BG","CA","CL","CO","CR","CY","CZ","DK","DO","DE","EC","EE","SV","FI","FR","GR","GT","HN","HK","HU","IS","IE","IT","LV","LT","LU","MY","MT","MX","NL","NZ","NI","NO","PA","PY","PE","PH","PL","PT","SG","SK","ES","SE","CH","TW","TR","UY","US","GB","AD","LI","MC","ID","JP","TH","VN","RO","IL","ZA","SA","AE","BH","QA","OM","KW","EG","MA","DZ","TN","LB","JO","PS","IN","BY","KZ","MD","UA","AL","BA","HR","ME","MK","RS","SI","KR","BD","PK","LK","GH","KE","NG","TZ","UG","AG","AM","BS","BB","BZ","BT","BW","BF","CV","CW","DM","FJ","GM","GE","GD","GW","GY","HT","JM","KI","LS","LR","MW","MV","ML","MH","FM","NA","NR","NE","PW","PG","WS","SM","ST","SN","SC","SL","SB","KN","LC","VC","SR","TL","TO","TT","TV","VU","AZ","BN","BI","KH","CM","TD","KM","GQ","SZ","GA","GN","KG","LA","MO","MR","MN","NP","RW","TG","UZ","ZW","BJ","MG","MU","MZ","AO","CI","DJ","ZM","CD","CG","IQ","LY","TJ","VE","ET","XK"],"disc_number":1,"duration_ms":160371,"episode":false,"explicit":false,"external_ids":{"isrc":"KRA302300278"},"external_urls":{"spotify":"https://open.spotify.com/track/4H65EdACzwqV8sTt3dDyA0"},"href":"https://api.spotify.com/v1/tracks/4H65EdACzwqV8sTt3dDyA0","id":"4H65EdACzwqV8sTt3dDyA0","is_local":false,"name":"Get A Guitar","popularity":73,"preview_url":"https://p.scdn.co/mp3-preview/c7a5918eacef90f1d25bb9e86178b3d1243785cf?cid=9451c6b72d894d47bb935b1079cf9f10","track":true,"track_number":1,"type":"track","uri":"spotify:track:4H65EdACzwqV8sTt3dDyA0"},"video_thumbnail":{"url":null},"lyricsData":{"lyrics":{"syncType":"LINE_SYNCED","lines":[{"startTimeMs":"2090","words":"If you want something to play with, get a guitar","syllables":[],"endTimeMs":"0"},{"startTimeMs":"6280","words":"너와 내 느낌대로, make it 시작해 봐","syllables":[],"endTimeMs":"0"},{"startTimeMs":"10200","words":"발 박자를 맞추고","syllables":[],"endTimeMs":"0"},{"startTimeMs":"12200","words":"손은 snapping like one, two, five","syllables":[],"endTimeMs":"0"},{"startTimeMs":"14760","words":"모두 집중해 줘 when I play the guitar","syllables":[],"endTimeMs":"0"},{"startTimeMs":"18430","words":"'Cause I know, you know?","syllables":[],"endTimeMs":"0"},{"startTimeMs":"19660","words":"Ooh, baby, ooh","syllables":[],"endTimeMs":"0"},{"startTimeMs":"21520","words":"I love it, 너와 맞추는 눈","syllables":[],"endTimeMs":"0"},{"startTimeMs":"23650","words":"Ooh, baby, ooh","syllables":[],"endTimeMs":"0"},{"startTimeMs":"25750","words":"I love it, 너와 맞추는 춤","syllables":[],"endTimeMs":"0"},{"startTimeMs":"27880","words":"Rhythm 속에 그려보는 햇살","syllables":[],"endTimeMs":"0"},{"startTimeMs":"30470","words":"가득 담은 꿈 in my heart","syllables":[],"endTimeMs":"0"},{"startTimeMs":"34660","words":"Tell me while you play me like","syllables":[],"endTimeMs":"0"},{"startTimeMs":"37070","words":"(Dun, dun, dun) still I love it, 너와 맞추는 눈, baby","syllables":[],"endTimeMs":"0"},{"startTimeMs":"41560","words":"(Dun, dun, dun) still I love it, 너와 맞추는 춤 (ah, yeah)","syllables":[],"endTimeMs":"0"},{"startTimeMs":"46020","words":"Get, get, get, get a guitar","syllables":[],"endTimeMs":"0"},{"startTimeMs":"47610","words":"Get, get, get, get a guitar (ooh)","syllables":[],"endTimeMs":"0"},{"startTimeMs":"50250","words":"Get, get, get, get a guitar","syllables":[],"endTimeMs":"0"},{"startTimeMs":"51940","words":"Get, get, get, get a guitar (eh)","syllables":[],"endTimeMs":"0"},{"startTimeMs":"53980","words":"If you want something to play with, get a guitar (get, get, get, get a guitar)","syllables":[],"endTimeMs":"0"},{"startTimeMs":"58450","words":"가볍게 툭 어깨에 메고 시작해 봐 (gеt, get, get, get a guitar)","syllables":[],"endTimeMs":"0"},{"startTimeMs":"62790","words":"Eh, 불타오를 lovе and youth (youth)","syllables":[],"endTimeMs":"0"},{"startTimeMs":"65420","words":"외치는 순간 feel the vibe (feel the vibe)","syllables":[],"endTimeMs":"0"},{"startTimeMs":"67390","words":"맘이 가는 대로 play it, get a guitar","syllables":[],"endTimeMs":"0"},{"startTimeMs":"70730","words":"'Cause I know, you know?","syllables":[],"endTimeMs":"0"},{"startTimeMs":"71980","words":"Ooh, baby, ooh (yeah, yeah)","syllables":[],"endTimeMs":"0"},{"startTimeMs":"74350","words":"I love it, 너와 맞추는 눈 (oh, baby)","syllables":[],"endTimeMs":"0"},{"startTimeMs":"76130","words":"Ooh, baby, ooh","syllables":[],"endTimeMs":"0"},{"startTimeMs":"78170","words":"I love it, 너와 맞추는 춤","syllables":[],"endTimeMs":"0"},{"startTimeMs":"80370","words":"Rhythm 속에 그려보는 햇살","syllables":[],"endTimeMs":"0"},{"startTimeMs":"82650","words":"가득 담은 꿈 in my heart","syllables":[],"endTimeMs":"0"},{"startTimeMs":"87060","words":"Tell me while you play me like","syllables":[],"endTimeMs":"0"},{"startTimeMs":"89460","words":"(Dun, dun, dun) still I love it, 너와 맞추는 눈, baby","syllables":[],"endTimeMs":"0"},{"startTimeMs":"93450","words":"(Dun, dun, dun) still I love it, 너와 맞추는 춤 (ah, yeah)","syllables":[],"endTimeMs":"0"},{"startTimeMs":"98760","words":"♪","syllables":[],"endTimeMs":"0"},{"startTimeMs":"101360","words":"Na-na, na-na-na-na, ooh","syllables":[],"endTimeMs":"0"},{"startTimeMs":"106320","words":"Baby","syllables":[],"endTimeMs":"0"},{"startTimeMs":"109590","words":"Get, get, get a, get a guitar","syllables":[],"endTimeMs":"0"},{"startTimeMs":"114530","words":"You got me, ooh","syllables":[],"endTimeMs":"0"},{"startTimeMs":"115750","words":"Ooh, baby, ooh (oh, baby)","syllables":[],"endTimeMs":"0"},{"startTimeMs":"117540","words":"I love it, 너와 맞추는 눈 (yeah, yeah, yeah)","syllables":[],"endTimeMs":"0"},{"startTimeMs":"120180","words":"Ooh, baby, ooh","syllables":[],"endTimeMs":"0"},{"startTimeMs":"121830","words":"I love it, 너와 맞추는 춤 (oh, I love it, 너와 맞추는 춤)","syllables":[],"endTimeMs":"0"},{"startTimeMs":"124320","words":"네가 원하던 그 순간","syllables":[],"endTimeMs":"0"},{"startTimeMs":"126540","words":"다른 생각들은 다 벗어나","syllables":[],"endTimeMs":"0"},{"startTimeMs":"130800","words":"Tell me while you play me like","syllables":[],"endTimeMs":"0"},{"startTimeMs":"133080","words":"(Dun, dun, dun) still I love it, 너와 맞추는 눈, baby","syllables":[],"endTimeMs":"0"},{"startTimeMs":"137270","words":"(Dun, dun, dun) still I love it, 너와 맞추는 춤 (ah, yeah)","syllables":[],"endTimeMs":"0"},{"startTimeMs":"141820","words":"Get, get, get, get a guitar","syllables":[],"endTimeMs":"0"},{"startTimeMs":"143630","words":"Get, get, get, get a guitar (woo, ah, yeah)","syllables":[],"endTimeMs":"0"},{"startTimeMs":"146230","words":"Get, get, get, get a guitar","syllables":[],"endTimeMs":"0"},{"startTimeMs":"147910","words":"Get, get, get, get a guitar","syllables":[],"endTimeMs":"0"},{"startTimeMs":"151110","words":"♪","syllables":[],"endTimeMs":"0"},{"startTimeMs":"157090","words":"Get, get, get, get a guitar","syllables":[],"endTimeMs":"0"},{"startTimeMs":"158580","words":"","syllables":[],"endTimeMs":"0"}],"provider":"MusixMatch","providerLyricsId":"161761333","providerDisplayName":"Musixmatch","syncLyricsUri":"","isDenseTypeface":true,"alternatives":[],"language":"ko","isRtlLanguage":false,"fullscreenAction":"FULLSCREEN_LYRICS","showUpsell":false},"colors":{"background":-14647385,"text":-16777216,"highlightText":-1},"hasVocalRemoval":false}}